fp_quant/__init__.py
fp_quant/module/__init__.py
fp_quant/module/linear.py
fp_quant/module/linear_fns.py
fp_quant/module/pseudoquant_linear_fns.py
fp_quant/module/triton/__init__.py
fp_quant/module/triton/mxfp4.py
fp_quant/module/triton/nvfp4.py
fp_quant/utils/__init__.py
fp_quant/utils/config.py
fp_quant/utils/replace.py
fp_quant-0.2.0.dist-info/METADATA
fp_quant-0.2.0.dist-info/WHEEL
fp_quant-0.2.0.dist-info/top_level.txt
fp_quant-0.2.0.dist-info/RECORD
